Metadata-Version: 1.1
Name: jobdiary
Version: 1.0.4
Summary: A funny and easy to use job diary
Home-page: https://github.com/fbarresi/JobDiary
Author: Federico Barresi
Author-email: fede.barresi@gmail.com
License: MIT
Platform: UNKNOWN
Classifier: Development Status :: 5 - Production/Stable
Classifier: Programming Language :: Python :: 3.5
Classifier: Programming Language :: Python :: 3.6
Classifier: Programming Language :: Python :: 3.7
Classifier: Environment :: Console
Classifier: Intended Audience :: Developers
Classifier: Intended Audience :: System Administrators
Classifier: License :: OSI Approved :: MIT License
Classifier: Topic :: Terminals
Classifier: Topic :: Text Processing
Classifier: Topic :: Utilities
